packageobspy/__init__.py
packageobspy/auth.py
packageobspy/const.py
packageobspy/exceptions.py
packageobspy/packageobs.py
packageobspy-1.0.0.dist-info/LICENSE
packageobspy-1.0.0.dist-info/METADATA
packageobspy-1.0.0.dist-info/WHEEL
packageobspy-1.0.0.dist-info/top_level.txt
packageobspy-1.0.0.dist-info/RECORD
