Metadata-Version: 2.1
Name: packageobspy
Version: 1.0.0
Summary: Package Observation from meteofrance.com
Author-email: Cyr-ius <cyr-ius@ipocus.net>
License: GPL-3
Keywords: meta,weather,async,meteofrance,meteo,france
Classifier: Programming Language :: Python
Classifier: Development Status :: 5 - Production/Stable
Classifier: License :: OSI Approved :: GNU General Public License v3 or later (GPLv3+)
Classifier: Programming Language :: Python :: 3
Classifier: Programming Language :: Python :: 3.11
Classifier: Programming Language :: Python :: 3.12
Classifier: Framework :: AsyncIO
Classifier: Intended Audience :: Developers
Classifier: Intended Audience :: System Administrators
Classifier: Topic :: Home Automation
Requires-Python: >=3.11.0
License-File: LICENSE
Requires-Dist: aiohttp >=3.9.5
